entrance/__init__.py
entrance/__main__.py
entrance/ws_handler.py
entrance/_util/__init__.py
entrance/_util/events.py
entrance/_util/logger.py
entrance/connection/__init__.py
entrance/connection/base.py
entrance/connection/cli.py
entrance/connection/netconf.py
entrance/connection/ssh.py
entrance/connection/threaded.py
entrance/feature/__init__.py
entrance/feature/base.py
entrance/feature/cfg_base.py
entrance/feature/cfg_core.py
entrance/feature/cfg_persist.py
entrance/feature/dyn_base.py
entrance/feature/tgt_base.py
entrance/feature/tgt_cli_config.py
entrance/feature/tgt_cli_exec.py
entrance/feature/tgt_group.py
entrance/feature/tgt_netconf.py
entrance/feature/tgt_syslog.py
entrance-1.0.1.dist-info/DESCRIPTION.rst
entrance-1.0.1.dist-info/METADATA
entrance-1.0.1.dist-info/RECORD
entrance-1.0.1.dist-info/WHEEL
entrance-1.0.1.dist-info/metadata.json
entrance-1.0.1.dist-info/top_level.txt
