Metadata-Version: 2.0
Name: entrance
Version: 1.0.1
Summary: Server framework for web apps
Home-page: https://github.com/ensoft/entrance
Author: Ensoft Ltd
Author-email: UNKNOWN
License: UNKNOWN
Platform: UNKNOWN
Classifier: Development Status :: 3 - Alpha
Classifier: Environment :: Web Environment
Classifier: License :: OSI Approved :: MIT License
Classifier: Programming Language :: Python :: 3.5
Classifier: Programming Language :: Python :: 3.6
Classifier: Programming Language :: Python :: 3.7
Requires-Dist: asyncio
Requires-Dist: janus
Requires-Dist: ncclient
Requires-Dist: paramiko
Requires-Dist: pyyaml
Requires-Dist: sanic
Requires-Dist: websockets (==6.0)
